vger/__init__.py
vger/application.py
vger/attack.py
vger/connection.py
vger/enumerate.py
vger/exploit.py
vger/menu.py
vger/persist.py
vger-0.2.6.dist-info/LICENSE
vger-0.2.6.dist-info/METADATA
vger-0.2.6.dist-info/WHEEL
vger-0.2.6.dist-info/entry_points.txt
vger-0.2.6.dist-info/RECORD
