Metadata-Version: 2.3
Name: vger
Version: 0.2.6
Summary: An execution framework for Jupyter environments.
License: GPL-3.0-only
Author: Joseph Lucas
Author-email: joe@joetl.com
Requires-Python: >=3.10,<4.0
Classifier: License :: OSI Approved :: GNU General Public License v3 (GPLv3)
Classifier: Programming Language :: Python :: 3
Classifier: Programming Language :: Python :: 3.10
Classifier: Programming Language :: Python :: 3.11
Classifier: Programming Language :: Python :: 3.12
Classifier: Programming Language :: Python :: 3.13
Provides-Extra: ai
Requires-Dist: inquirer (>=3.2,<4.0)
Requires-Dist: pyds-sum ; extra == "ai"
Requires-Dist: pytest (>=8.3.5,<9.0.0)
Requires-Dist: requests (>=2.30,<3.0)
Requires-Dist: rich (>=13.7,<14.0)
Requires-Dist: typer[all] (>=0.9.0,<0.10.0)
Requires-Dist: urllib3 (>=2.1,<3.0)
Requires-Dist: websockets (>=12.0,<13.0)
